randatoms/__init__.py
randatoms/constants.py
randatoms/converter.py
randatoms/dataloader.py
randatoms/merger.py
randatoms/utils.py
randatoms/dataset/__init__.py
randatoms/dataset/default.tar
test/test_converter.py
test/test_dataloader.py
test/test_merger.py
randatoms-0.0.1.dist-info/LICENSE
randatoms-0.0.1.dist-info/METADATA
randatoms-0.0.1.dist-info/WHEEL
randatoms-0.0.1.dist-info/top_level.txt
randatoms-0.0.1.dist-info/RECORD
