Metadata-Version: 2.1
Name: randatoms
Version: 0.0.1
Summary: A random atoms package for atomistic scientists: easily generate, filter, and manage atomic datasets.
Author-email: Mingi KANG <kangmg@korea.ac.kr>
License: MIT
Requires-Python: >=3.8
License-File: LICENSE
Requires-Dist: h5py>=3.0.0
Requires-Dist: numpy>=1.20.0
Requires-Dist: pandas>=1.2.0
Requires-Dist: ase>=3.22.0
Requires-Dist: tqdm>=4.60.0
